odoo/addons/easy_my_coop_fr/README.rst
odoo/addons/easy_my_coop_fr/__init__.py
odoo/addons/easy_my_coop_fr/__manifest__.py
odoo/addons/easy_my_coop_fr/i18n/easy_my_coop_fr.pot
odoo/addons/easy_my_coop_fr/models/__init__.py
odoo/addons/easy_my_coop_fr/models/partner.py
odoo/addons/easy_my_coop_fr/models/subscription_request.py
odoo/addons/easy_my_coop_fr/readme/CONTRIBUTORS.rst
odoo/addons/easy_my_coop_fr/readme/DESCRIPTION.rst
odoo/addons/easy_my_coop_fr/static/description/index.html
odoo/addons/easy_my_coop_fr/views/certificate_template.xml
odoo12_addon_easy_my_coop_fr-12.0.1.1.0.dist-info/METADATA
odoo12_addon_easy_my_coop_fr-12.0.1.1.0.dist-info/WHEEL
odoo12_addon_easy_my_coop_fr-12.0.1.1.0.dist-info/top_level.txt
odoo12_addon_easy_my_coop_fr-12.0.1.1.0.dist-info/RECORD
