Metadata-Version: 2.1
Name: odoo12-addon-easy-my-coop-fr
Version: 12.0.1.1.0
Summary: This is the french localization for the easy my coop module
Home-page: https://coopiteasy.be
Author: Coop IT Easy SCRLfs
License: AGPL-3
Platform: UNKNOWN
Classifier: Programming Language :: Python
Classifier: Framework :: Odoo
Classifier: Framework :: Odoo :: 12.0
Classifier: License :: OSI Approved :: GNU Affero General Public License v3
Requires-Python: >=3.5
Requires-Dist: odoo12-addon-easy-my-coop
Requires-Dist: odoo12-addon-easy-my-coop-website
Requires-Dist: odoo (<12.1dev,>=12.0a)
